[{
    "id": "1",
    "idProd": "1",
    "score": 3,
    "description": "Ya llevo un año con este auto y la verdad que tiene sus ventajas y desventajas",
    "user": "juan_pedro",
    "dateTime": "2020-02-25 18:03:52"
},
{
    "id": "2",
    "idProd": "1",
    "score": 5,
    "description": "Es un auto muy cómodo y en relación precio/calidad vale la pena!",
    "user": "maria_sanchez",
    "dateTime": "2020-01-17 13:42:18"
},
{
    "id": "3",
    "idProd": "1",
    "score": 4,
    "description": "Casi todo bien!, excepto por algún detalle de gusto personal",
    "user": "paola_perez",
    "dateTime": "2020-03-14 09:05:13"
},
{
    "id": "4",
    "idProd": "1",
    "score": 5,
    "description": "Un espectáculo el auto!",
    "user": "pablo_gomez",
    "dateTime": "2020-02-21 15:05:22"
},


{
    "id": "1",
    "idProd": "2",
    "score": 4,
    "description": "Lo uso hace tiempo y sigue genial.",
    "user": "john_titor",
    "dateTime": "2020-02-28 19:03:32"
},
{
    "id": "2",
    "idProd": "2",
    "score": 3.5,
    "description": "Lindo, cómodo y seguro, recomiendo.",
    "user": "lauta_rod",
    "dateTime": "2020-01-13 12:22:08"
},
{
    "id": "3",
    "idProd": "2",
    "score": 4,
    "description": "ME ENCANTÓ!",
    "user": "chester_bennington",
    "dateTime": "2021-08-14 09:02:33"
},
{
    "id": "4",
    "idProd": "2",
    "score": 4.5,
    "description": "Fiat Uno, que nostalgia, maravilloso auto.",
    "user": "mike_shinoda",
    "dateTime": "2021-08-25 13:15:22"
},


{
    "id": "1",
    "idProd": "3",
    "score": 2,
    "description": "No lo recomiendo, poco espacio!",
    "user": "homero_lópez",
    "dateTime": "2019-03-22 12:05:52"
},
{
    "id": "2",
    "idProd": "3",
    "score": 1,
    "description": "Quiero el reembolso! Le gasté la plata a mi abuela al pedo...",
    "user": "maria_juana",
    "dateTime": "2020-01-02 11:52:18"
},
{
    "id": "3",
    "idProd": "3",
    "score": 2,
    "description": "Malísimo, consume mucho y poco espacio.",
    "user": "lalo_garza",
    "dateTime": "2020-02-14 13:45:13"
},
{
    "id": "4",
    "idProd": "3",
    "score": 3,
    "description": "Puede estar mejor.",
    "user": "mica_cabj",
    "dateTime": "2020-02-03 15:33:22"
},


{
    "id": "1",
    "idProd": "4",
    "score": 4,
    "description": "Impecable el nene",
    "user": "tony_pachecho",
    "dateTime": "2020-12-16 13:05:52"
},
{
    "id": "2",
    "idProd": "4",
    "score": 5,
    "description": "Totalmente recomendado! Un lujo el auto",
    "user": "mati_silva",
    "dateTime": "2020-01-27 16:20:00"
},
{
    "id": "3",
    "idProd": "4",
    "score": 4.5,
    "description": "Una máquina, fiera, mastodonte.",
    "user": "juan_carlos",
    "dateTime": "2021-05-30 07:45:13"
},
{
    "id": "4",
    "idProd": "4",
    "score": 5,
    "description": "SOÑADO! Muy cómodo el interior, vale la pena.",
    "user": "agus_lima",
    "dateTime": "2020-08-31 15:34:22"
}]